gitlab_runner_api/__init__.py
gitlab_runner_api/cli.py
gitlab_runner_api/exceptions.py
gitlab_runner_api/failure_reasons.py
gitlab_runner_api/job.py
gitlab_runner_api/logging.py
gitlab_runner_api/runner.py
gitlab_runner_api/version.py
gitlab_runner_api/testing/__init__.py
gitlab_runner_api/testing/job.py
gitlab_runner_api/testing/runner.py
gitlab_runner_api/testing/utils.py
gitlab_runner_api/utils/__init__.py
gitlab_runner_api/utils/ansi.py
gitlab_runner_api-1.0.4.data/data/README.rst
gitlab_runner_api-1.0.4.dist-info/LICENSE.txt
gitlab_runner_api-1.0.4.dist-info/METADATA
gitlab_runner_api-1.0.4.dist-info/WHEEL
gitlab_runner_api-1.0.4.dist-info/entry_points.txt
gitlab_runner_api-1.0.4.dist-info/top_level.txt
gitlab_runner_api-1.0.4.dist-info/RECORD
