Metadata-Version: 2.1
Name: gitlab-runner-api
Version: 1.0.4
Summary: Unofficial implementation of the GitLab runner client for making customised CI runners
Home-page: https://github.com/chrisburr/gitlab-runner-api/
License: MIT
Platform: UNKNOWN
Classifier: Programming Language :: Python :: 2
Classifier: Programming Language :: Python :: 2.7
Classifier: Programming Language :: Python :: 3
Classifier: Programming Language :: Python :: 3.5
Classifier: Programming Language :: Python :: 3.6
Classifier: Programming Language :: Python :: 3.7
Classifier: Programming Language :: Python :: 3.8
Classifier: Programming Language :: Python :: 3.9
Classifier: License :: OSI Approved :: MIT License
Requires-Python: >=2.7,!=3.0.*,!=3.1.*,!=3.2.*,!=3.3.*,!=3.4.*
Requires-Dist: setuptools
Requires-Dist: colorlog
Requires-Dist: requests
Requires-Dist: six
Provides-Extra: testing
Requires-Dist: pytest ; extra == 'testing'
Requires-Dist: pytest-cov ; extra == 'testing'
Requires-Dist: responses ; extra == 'testing'
Requires-Dist: requests-toolbelt ; extra == 'testing'
